prosrs/__init__.py
prosrs/version.py
prosrs/optimizer/__init__.py
prosrs/optimizer/optimizer.py
prosrs/optimizer/surrogate.py
prosrs/problem/__init__.py
prosrs/problem/benchmark.py
prosrs/problem/problem.py
prosrs/utility/__init__.py
prosrs/utility/classes.py
prosrs/utility/constants.py
prosrs/utility/functions.py
prosrs-1.1.0.dist-info/LICENSE
prosrs-1.1.0.dist-info/METADATA
prosrs-1.1.0.dist-info/WHEEL
prosrs-1.1.0.dist-info/top_level.txt
prosrs-1.1.0.dist-info/RECORD
