Metadata-Version: 2.1
Name: prosrs
Version: 1.1.0
Summary: A tree-based parallel surrogate optimization algorithm for optimizing noisy expensive functions
Home-page: https://github.com/compdyn/ProSRS
Author: Chenchao Shou
Author-email: cshou3@illinois.edu
License: University of Illinois/NCSA Open Source
Keywords: optimization algorithm
Platform: UNKNOWN
Classifier: Programming Language :: Python :: 2
Classifier: Programming Language :: Python :: 2.7
Classifier: Programming Language :: Python :: 3
Classifier: Programming Language :: Python :: 3.7
Classifier: Natural Language :: English
Classifier: Operating System :: MacOS :: MacOS X
Classifier: Operating System :: Microsoft :: Windows
Classifier: Operating System :: POSIX :: Linux
Classifier: License :: OSI Approved :: University of Illinois/NCSA Open Source License
Classifier: Intended Audience :: Developers
Classifier: Intended Audience :: Science/Research
Classifier: Topic :: Scientific/Engineering
Classifier: Topic :: Software Development
Requires-Dist: numpy
Requires-Dist: scipy
Requires-Dist: matplotlib
Requires-Dist: pyDOE
Requires-Dist: pathos
Requires-Dist: scikit-learn
